{"active":false,"connections":{"When clicking ‘Execute workflow’":{"main":[[{"index":0,"node":"Ein Test Node","type":"main"}]]}},"name":"Test Workflow","nodes":[{"name":"When clicking ‘Execute workflow’","parameters":{},"position":[0,0],"type":"n8n-nodes-base.manualTrigger","typeVersion":1},{"name":"Ein Test Node","parameters":{"options":{}},"position":[208,0],"type":"n8n-nodes-base.set","typeVersion":3.4}],"settings":{"availableInMCP":false,"callerPolicy":"workflowsFromSameOwner","executionOrder":"v1"}}